llama_index/multi_modal_llms/ollama/__init__.py
llama_index/multi_modal_llms/ollama/base.py
llama_index_multi_modal_llms_ollama-0.6.1.dist-info/METADATA
llama_index_multi_modal_llms_ollama-0.6.1.dist-info/WHEEL
llama_index_multi_modal_llms_ollama-0.6.1.dist-info/licenses/LICENSE
llama_index_multi_modal_llms_ollama-0.6.1.dist-info/RECORD
